brokerstream/__init__.py
brokerstream/kafka_stream.py
brokerstream-0.0.13.dist-info/METADATA
brokerstream-0.0.13.dist-info/WHEEL
brokerstream-0.0.13.dist-info/top_level.txt
brokerstream-0.0.13.dist-info/RECORD
